{
  "generated_at_utc": "2026-01-14T10:14:44Z",
  "items": [
    {
      "type": "crypto",
      "symbol": "BTCUSDT",
      "display": "BTC/USDT",
      "price": 95111.0,
      "change_pct_24h": 3.22618,
      "volume_24h": 67680810131.0,
      "rvol": null,
      "volume_label": null,
      "trend": "bullish",
      "source_name": "CoinGecko",
      "source_url": "https://www.tradingview.com/symbols/BTCUSDT/",
      "last_update_utc": "2026-01-14T10:14:35Z"
    },
    {
      "type": "crypto",
      "symbol": "ETHUSDT",
      "display": "ETH/USDT",
      "price": 3329.25,
      "change_pct_24h": 6.24215,
      "volume_24h": 36267703458.0,
      "rvol": null,
      "volume_label": null,
      "trend": "bullish",
      "source_name": "CoinGecko",
      "source_url": "https://www.tradingview.com/symbols/ETHUSDT/",
      "last_update_utc": "2026-01-14T10:14:35Z"
    },
    {
      "type": "crypto",
      "symbol": "SOLUSDT",
      "display": "SOL/USDT",
      "price": 145.54,
      "change_pct_24h": 2.46957,
      "volume_24h": 7459842547.0,
      "rvol": null,
      "volume_label": null,
      "trend": "bullish",
      "source_name": "CoinGecko",
      "source_url": "https://www.tradingview.com/symbols/SOLUSDT/",
      "last_update_utc": "2026-01-14T10:14:35Z"
    },
    {
      "type": "crypto",
      "symbol": "BNBUSDT",
      "display": "BNB/USDT",
      "price": 937.66,
      "change_pct_24h": 3.1191,
      "volume_24h": 2630408116.0,
      "rvol": null,
      "volume_label": null,
      "trend": "bullish",
      "source_name": "CoinGecko",
      "source_url": "https://www.tradingview.com/symbols/BNBUSDT/",
      "last_update_utc": "2026-01-14T10:14:35Z"
    },
    {
      "type": "crypto",
      "symbol": "XRPUSDT",
      "display": "XRP/USDT",
      "price": 2.15,
      "change_pct_24h": 3.94923,
      "volume_24h": 4507415487.0,
      "rvol": null,
      "volume_label": null,
      "trend": "bullish",
      "source_name": "CoinGecko",
      "source_url": "https://www.tradingview.com/symbols/XRPUSDT/",
      "last_update_utc": "2026-01-14T10:14:35Z"
    },
    {
      "type": "crypto",
      "symbol": "ADAUSDT",
      "display": "ADA/USDT",
      "price": 0.420317,
      "change_pct_24h": 6.91082,
      "volume_24h": 901363582.0,
      "rvol": null,
      "volume_label": null,
      "trend": "bullish",
      "source_name": "CoinGecko",
      "source_url": "https://www.tradingview.com/symbols/ADAUSDT/",
      "last_update_utc": "2026-01-14T10:14:35Z"
    },
    {
      "type": "crypto",
      "symbol": "DOGEUSDT",
      "display": "DOGE/USDT",
      "price": 0.148132,
      "change_pct_24h": 5.99398,
      "volume_24h": 1789603959.0,
      "rvol": null,
      "volume_label": null,
      "trend": "bullish",
      "source_name": "CoinGecko",
      "source_url": "https://www.tradingview.com/symbols/DOGEUSDT/",
      "last_update_utc": "2026-01-14T10:14:35Z"
    },
    {
      "type": "crypto",
      "symbol": "AVAXUSDT",
      "display": "AVAX/USDT",
      "price": 14.68,
      "change_pct_24h": 6.30555,
      "volume_24h": 589540763.0,
      "rvol": null,
      "volume_label": null,
      "trend": "bullish",
      "source_name": "CoinGecko",
      "source_url": "https://www.tradingview.com/symbols/AVAXUSDT/",
      "last_update_utc": "2026-01-14T10:14:35Z"
    },
    {
      "type": "crypto",
      "symbol": "LINKUSDT",
      "display": "LINK/USDT",
      "price": 14.09,
      "change_pct_24h": 6.14588,
      "volume_24h": 649010759.0,
      "rvol": null,
      "volume_label": null,
      "trend": "bullish",
      "source_name": "CoinGecko",
      "source_url": "https://www.tradingview.com/symbols/LINKUSDT/",
      "last_update_utc": "2026-01-14T10:14:35Z"
    },
    {
      "type": "crypto",
      "symbol": "MATICUSDT",
      "display": "MATIC/USDT",
      "price": 0.161127,
      "change_pct_24h": 6.38718,
      "volume_24h": 243457145.0,
      "rvol": null,
      "volume_label": null,
      "trend": "bullish",
      "source_name": "CoinGecko",
      "source_url": "https://www.tradingview.com/symbols/MATICUSDT/",
      "last_update_utc": "2026-01-14T10:14:35Z"
    },
    {
      "type": "crypto",
      "symbol": "DOTUSDT",
      "display": "DOT/USDT",
      "price": 2.28,
      "change_pct_24h": 9.64746,
      "volume_24h": 313518060.0,
      "rvol": null,
      "volume_label": null,
      "trend": "bullish",
      "source_name": "CoinGecko",
      "source_url": "https://www.tradingview.com/symbols/DOTUSDT/",
      "last_update_utc": "2026-01-14T10:14:35Z"
    },
    {
      "type": "crypto",
      "symbol": "TRXUSDT",
      "display": "TRX/USDT",
      "price": 0.302211,
      "change_pct_24h": 1.12267,
      "volume_24h": 748456302.0,
      "rvol": null,
      "volume_label": null,
      "trend": "bullish",
      "source_name": "CoinGecko",
      "source_url": "https://www.tradingview.com/symbols/TRXUSDT/",
      "last_update_utc": "2026-01-14T10:14:35Z"
    },
    {
      "type": "crypto",
      "symbol": "LTCUSDT",
      "display": "LTC/USDT",
      "price": 79.01,
      "change_pct_24h": 3.73029,
      "volume_24h": 1046824464.0,
      "rvol": null,
      "volume_label": null,
      "trend": "bullish",
      "source_name": "CoinGecko",
      "source_url": "https://www.tradingview.com/symbols/LTCUSDT/",
      "last_update_utc": "2026-01-14T10:14:35Z"
    },
    {
      "type": "crypto",
      "symbol": "BCHUSDT",
      "display": "BCH/USDT",
      "price": 604.02,
      "change_pct_24h": -1.4035,
      "volume_24h": 603632819.0,
      "rvol": null,
      "volume_label": null,
      "trend": "bearish",
      "source_name": "CoinGecko",
      "source_url": "https://www.tradingview.com/symbols/BCHUSDT/",
      "last_update_utc": "2026-01-14T10:14:35Z"
    },
    {
      "type": "crypto",
      "symbol": "UNIUSDT",
      "display": "UNI/USDT",
      "price": 5.8,
      "change_pct_24h": 7.05063,
      "volume_24h": 357843671.0,
      "rvol": null,
      "volume_label": null,
      "trend": "bullish",
      "source_name": "CoinGecko",
      "source_url": "https://www.tradingview.com/symbols/UNIUSDT/",
      "last_update_utc": "2026-01-14T10:14:35Z"
    },
    {
      "type": "crypto",
      "symbol": "ATOMUSDT",
      "display": "ATOM/USDT",
      "price": 2.68,
      "change_pct_24h": 5.19503,
      "volume_24h": 71699640.0,
      "rvol": null,
      "volume_label": null,
      "trend": "bullish",
      "source_name": "CoinGecko",
      "source_url": "https://www.tradingview.com/symbols/ATOMUSDT/",
      "last_update_utc": "2026-01-14T10:14:35Z"
    },
    {
      "type": "crypto",
      "symbol": "ICPUSDT",
      "display": "ICP/USDT",
      "price": 3.86,
      "change_pct_24h": 19.22538,
      "volume_24h": 318543392.0,
      "rvol": null,
      "volume_label": null,
      "trend": "bullish",
      "source_name": "CoinGecko",
      "source_url": "https://www.tradingview.com/symbols/ICPUSDT/",
      "last_update_utc": "2026-01-14T10:14:35Z"
    },
    {
      "type": "crypto",
      "symbol": "FILUSDT",
      "display": "FIL/USDT",
      "price": 1.59,
      "change_pct_24h": 6.61841,
      "volume_24h": 219579195.0,
      "rvol": null,
      "volume_label": null,
      "trend": "bullish",
      "source_name": "CoinGecko",
      "source_url": "https://www.tradingview.com/symbols/FILUSDT/",
      "last_update_utc": "2026-01-14T10:14:35Z"
    },
    {
      "type": "crypto",
      "symbol": "APTUSDT",
      "display": "APT/USDT",
      "price": 1.95,
      "change_pct_24h": 8.42348,
      "volume_24h": 159587472.0,
      "rvol": null,
      "volume_label": null,
      "trend": "bullish",
      "source_name": "CoinGecko",
      "source_url": "https://www.tradingview.com/symbols/APTUSDT/",
      "last_update_utc": "2026-01-14T10:14:35Z"
    },
    {
      "type": "crypto",
      "symbol": "ARBUSDT",
      "display": "ARB/USDT",
      "price": 0.224231,
      "change_pct_24h": 8.97672,
      "volume_24h": 161570449.0,
      "rvol": null,
      "volume_label": null,
      "trend": "bullish",
      "source_name": "CoinGecko",
      "source_url": "https://www.tradingview.com/symbols/ARBUSDT/",
      "last_update_utc": "2026-01-14T10:14:35Z"
    },
    {
      "type": "stock",
      "symbol": "^GSPC",
      "display": "^GSPC",
      "price": 6963.74,
      "change_pct_1d": -0.19391538524380816,
      "volume": null,
      "rvol": null,
      "volume_label": null,
      "trend": "bearish",
      "source_name": "Stooq",
      "source_url": "https://www.tradingview.com/symbols/GSPC/",
      "last_update_utc": "2026-01-14T10:14:39Z"
    },
    {
      "type": "stock",
      "symbol": "^NDX",
      "display": "^NDX",
      "price": 25741.95,
      "change_pct_1d": -0.1772553228947455,
      "volume": null,
      "rvol": null,
      "volume_label": null,
      "trend": "bearish",
      "source_name": "Stooq",
      "source_url": "https://www.tradingview.com/symbols/NDX/",
      "last_update_utc": "2026-01-14T10:14:39Z"
    },
    {
      "type": "stock",
      "symbol": "^DJI",
      "display": "^DJI",
      "price": 49191.99,
      "change_pct_1d": -0.8030013994700549,
      "volume": null,
      "rvol": null,
      "volume_label": null,
      "trend": "bearish",
      "source_name": "Stooq",
      "source_url": "https://www.tradingview.com/symbols/DJI/",
      "last_update_utc": "2026-01-14T10:14:41Z"
    },
    {
      "type": "stock",
      "symbol": "AAPL",
      "display": "AAPL",
      "price": 261.05,
      "change_pct_1d": 0.30739673390970657,
      "volume": null,
      "rvol": null,
      "volume_label": null,
      "trend": "bullish",
      "source_name": "Stooq",
      "source_url": "https://www.tradingview.com/symbols/AAPL/",
      "last_update_utc": "2026-01-14T10:14:42Z"
    },
    {
      "type": "stock",
      "symbol": "MSFT",
      "display": "MSFT",
      "price": 470.67,
      "change_pct_1d": -1.3642650572111135,
      "volume": null,
      "rvol": null,
      "volume_label": null,
      "trend": "bearish",
      "source_name": "Stooq",
      "source_url": "https://www.tradingview.com/symbols/MSFT/",
      "last_update_utc": "2026-01-14T10:14:42Z"
    },
    {
      "type": "stock",
      "symbol": "NVDA",
      "display": "NVDA",
      "price": 185.81,
      "change_pct_1d": 0.4704228398399506,
      "volume": null,
      "rvol": null,
      "volume_label": null,
      "trend": "bullish",
      "source_name": "Stooq",
      "source_url": "https://www.tradingview.com/symbols/NVDA/",
      "last_update_utc": "2026-01-14T10:14:42Z"
    },
    {
      "type": "stock",
      "symbol": "AMZN",
      "display": "AMZN",
      "price": 242.6,
      "change_pct_1d": -1.5701708118635145,
      "volume": null,
      "rvol": null,
      "volume_label": null,
      "trend": "bearish",
      "source_name": "Stooq",
      "source_url": "https://www.tradingview.com/symbols/AMZN/",
      "last_update_utc": "2026-01-14T10:14:43Z"
    },
    {
      "type": "stock",
      "symbol": "TSLA",
      "display": "TSLA",
      "price": 447.2,
      "change_pct_1d": -0.3920171062009959,
      "volume": null,
      "rvol": null,
      "volume_label": null,
      "trend": "bearish",
      "source_name": "Stooq",
      "source_url": "https://www.tradingview.com/symbols/TSLA/",
      "last_update_utc": "2026-01-14T10:14:43Z"
    },
    {
      "type": "stock",
      "symbol": "GOOGL",
      "display": "GOOGL",
      "price": 335.97,
      "change_pct_1d": 1.2384740553245386,
      "volume": null,
      "rvol": null,
      "volume_label": null,
      "trend": "bullish",
      "source_name": "Stooq",
      "source_url": "https://www.tradingview.com/symbols/GOOGL/",
      "last_update_utc": "2026-01-14T10:14:43Z"
    },
    {
      "type": "stock",
      "symbol": "META",
      "display": "META",
      "price": 631.09,
      "change_pct_1d": -1.6947832453229894,
      "volume": null,
      "rvol": null,
      "volume_label": null,
      "trend": "bearish",
      "source_name": "Stooq",
      "source_url": "https://www.tradingview.com/symbols/META/",
      "last_update_utc": "2026-01-14T10:14:43Z"
    },
    {
      "type": "fx",
      "symbol": "USD/PKR",
      "display": "USD/PKR",
      "price": 279.45,
      "change_pct_1d": -0.15,
      "trend": "sideways",
      "source_name": "ReferenceSource",
      "source_url": "https://www.tradingview.com/symbols/USDPKR/",
      "last_update_utc": "2026-01-14T10:14:43Z"
    },
    {
      "type": "fx",
      "symbol": "EUR/USD",
      "display": "EUR/USD",
      "price": 1.0864,
      "change_pct_1d": 0.07,
      "trend": "bullish",
      "source_name": "ReferenceSource",
      "source_url": "https://www.tradingview.com/symbols/EURUSD/",
      "last_update_utc": "2026-01-14T10:14:43Z"
    }
  ]
}